hallucinate_app/index.py
hallucinate_app/ipfs_kit.py
hallucinate_app-0.0.2.dist-info/METADATA
hallucinate_app-0.0.2.dist-info/WHEEL
hallucinate_app-0.0.2.dist-info/top_level.txt
hallucinate_app-0.0.2.dist-info/RECORD
